dexterous_gym/__init__.py
dexterous_gym/core/__init__.py
dexterous_gym/core/two_hand_robot_env.py
dexterous_gym/core/two_hands_env.py
dexterous_gym/envs/__init__.py
dexterous_gym/envs/block_catch_overarm.py
dexterous_gym/envs/block_catch_underarm.py
dexterous_gym/envs/block_catch_underarm_hard.py
dexterous_gym/envs/block_hand_over.py
dexterous_gym/envs/egg_catch_overarm.py
dexterous_gym/envs/egg_catch_underarm.py
dexterous_gym/envs/egg_catch_underarm_hard.py
dexterous_gym/envs/egg_hand_over.py
dexterous_gym/envs/pen_catch_overarm.py
dexterous_gym/envs/pen_catch_underarm.py
dexterous_gym/envs/pen_catch_underarm_hard.py
dexterous_gym/envs/pen_hand_over.py
dexterous_gym/envs/pen_spin.py
dexterous_gym/envs/two_block_catch_underarm.py
dexterous_gym/envs/two_egg_catch_underarm.py
dexterous_gym/envs/two_pen_catch_underarm.py
dexterous_gym/envs/hand/block_catch_overarm.xml
dexterous_gym/envs/hand/block_catch_underarm.xml
dexterous_gym/envs/hand/block_catch_underarm_hard.xml
dexterous_gym/envs/hand/block_handover.xml
dexterous_gym/envs/hand/egg_catch_overarm.xml
dexterous_gym/envs/hand/egg_catch_underarm.xml
dexterous_gym/envs/hand/egg_catch_underarm_hard.xml
dexterous_gym/envs/hand/egg_handover.xml
dexterous_gym/envs/hand/manipulate_pen.xml
dexterous_gym/envs/hand/pen_catch_overarm.xml
dexterous_gym/envs/hand/pen_catch_underarm.xml
dexterous_gym/envs/hand/pen_catch_underarm_hard.xml
dexterous_gym/envs/hand/pen_handover.xml
dexterous_gym/envs/hand/robot.xml
dexterous_gym/envs/hand/shared.xml
dexterous_gym/envs/hand/shared_asset.xml
dexterous_gym/envs/hand/shared_two.xml
dexterous_gym/envs/hand/two_block_catch_underarm.xml
dexterous_gym/envs/hand/two_egg_catch_underarm.xml
dexterous_gym/envs/hand/two_pen_catch_underarm.xml
dexterous_gym/envs/stls/hand/F1.stl
dexterous_gym/envs/stls/hand/F2.stl
dexterous_gym/envs/stls/hand/F3.stl
dexterous_gym/envs/stls/hand/TH1_z.stl
dexterous_gym/envs/stls/hand/TH2_z.stl
dexterous_gym/envs/stls/hand/TH3_z.stl
dexterous_gym-0.1.7.dist-info/METADATA
dexterous_gym-0.1.7.dist-info/WHEEL
dexterous_gym-0.1.7.dist-info/top_level.txt
dexterous_gym-0.1.7.dist-info/RECORD
