Metadata-Version: 2.1
Name: dexterous-gym
Version: 0.1.7
Summary: Challenging extensions to openAI Gyms hand manipulation environments
Home-page: http://github.com/henrycharlesworth/dexterous_gym
Author: Henry Charlesworth
Author-email: H.Charlesworth@warwick.ac.uk
License: UNKNOWN
Platform: UNKNOWN
